easy_gradcam/__init__.py
easy_gradcam/classification.py
easy_gradcam/env_check.py
easy_gradcam/visualization.py
easy_gradcam-0.0.5.dist-info/licenses/LICENSE
easy_gradcam-0.0.5.dist-info/METADATA
easy_gradcam-0.0.5.dist-info/WHEEL
easy_gradcam-0.0.5.dist-info/top_level.txt
easy_gradcam-0.0.5.dist-info/RECORD
