Metadata-Version: 2.4
Name: easy_gradcam
Version: 0.0.5
Summary: GradCAM for torchvision, timm and huggingface model.
Author-email: "PoYung Chou, YuYung Kao, *PoHusn Feng" <benfeng99@gmail.com>
License: MIT License
Project-URL: Homepage, https://github.com/breeze0305/easy_gradcam
Project-URL: Issues, https://github.com/breeze0305/easy_gradcam/issues
Keywords: easy to use(I hope),gradcam
Classifier: Programming Language :: Python :: 3
Classifier: Operating System :: OS Independent
Requires-Python: >=3.9
License-File: LICENSE
Requires-Dist: numpy
Requires-Dist: matplotlib
Requires-Dist: seaborn
Requires-Dist: opencv-python
Dynamic: license-file
